setup.py
enpkg_interfaces/__init__.py
enpkg_interfaces/__version__.py
enpkg_interfaces/sample.py
enpkg_interfaces/specter.py
enpkg_interfaces/taxon.py
enpkg_interfaces/user.py
enpkg_interfaces.egg-info/PKG-INFO
enpkg_interfaces.egg-info/SOURCES.txt
enpkg_interfaces.egg-info/dependency_links.txt
enpkg_interfaces.egg-info/top_level.txt